lsm_storage_engine/__init__.py
lsm_storage_engine/abstract_kv_store.py
lsm_storage_engine/cli.py
lsm_storage_engine/server.py
lsm_storage_engine/storage_manager.py
lsm_storage_engine/lsm_tree/lsm_store.py
lsm_storage_engine/lsm_tree/memtable.py
lsm_storage_engine/lsm_tree/sstable.py
lsm_storage_engine/lsm_tree/wal.py
lsm_storage_engine_key_value_store-1.2.3.dist-info/licenses/LICENSE
lsm_storage_engine_key_value_store-1.2.3.dist-info/METADATA
lsm_storage_engine_key_value_store-1.2.3.dist-info/WHEEL
lsm_storage_engine_key_value_store-1.2.3.dist-info/entry_points.txt
lsm_storage_engine_key_value_store-1.2.3.dist-info/top_level.txt
lsm_storage_engine_key_value_store-1.2.3.dist-info/RECORD
