Metadata-Version: 2.4
Name: lsm-storage-engine-key-value-store
Version: 1.2.3
Summary: A persistent key-value storage engine based on LSM-tree architecture.
Author-email: Shashank <shashankshashidhar73@gmail.com>
License: MIT
Project-URL: Homepage, https://github.com/Shashank1985/storage-engine
Project-URL: Issues, https://github.com/Shashank1985/storage-engine/issues
Classifier: Development Status :: 4 - Beta
Classifier: Programming Language :: Python :: 3
Classifier: License :: OSI Approved :: MIT License
Classifier: Operating System :: OS Independent
Classifier: Topic :: Database
Classifier: Topic :: System :: Filesystems
Classifier: Environment :: Console
Requires-Python: >=3.8
License-File: LICENSE
Requires-Dist: sortedcontainers
Requires-Dist: mmh3
Requires-Dist: fastapi
Requires-Dist: uvicorn
Requires-Dist: requests
Requires-Dist: msgpack
Dynamic: license-file
